{
  "model": {
    "network": {
      "layers": [
        {
          "filters": 40,
          "kernelSize": {
            "x": 3,
            "y": 3
          },
          "stride": {
            "x": 1,
            "y": 1
          }
        },
        {
          "type": "MAX_POOLING",
          "kernelSize": {
            "x": 2,
            "y": 2
          },
          "stride": {
            "x": 2,
            "y": 2
          }
        },
        {
          "filters": 60,
          "kernelSize": {
            "x": 3,
            "y": 3
          },
          "stride": {
            "x": 1,
            "y": 1
          }
        },
        {
          "type": "MAX_POOLING",
          "kernelSize": {
            "x": 2,
            "y": 2
          },
          "stride": {
            "x": 2,
            "y": 2
          }
        },
        {
          "type": "LSTM",
          "hiddenNodes": 200
        }
      ],
      "solver": "ADAM_SOLVER",
      "dropout": 0.5,
      "features": 48,
      "classes": 111,
      "backend": {
        "cudnn": true,
        "randomSeed": 4,
        "shuffleBufferSize": 1000
      },
      "ctcMergeRepeated": true,
      "learningRate": 0.0010000000474974513
    },
    "lineHeight": 48,
    "dataPreprocessor": {
      "type": "MULTI_NORMALIZER",
      "children": [
        {
          "lineHeight": 48,
          "pad": 16
        }
      ]
    },
    "textPreprocessor": {
      "type": "MULTI_NORMALIZER",
      "children": [
        {
          "type": "TEXT_NORMALIZER"
        },
        {
          "type": "TEXT_REGULARIZER",
          "replacements": [
            {
              "old": "\\s+(?u)",
              "new": " ",
              "regex": true
            },
            {
              "old": "\\n(?u)",
              "regex": true
            },
            {
              "old": "^\\s+(?u)",
              "regex": true
            },
            {
              "old": "\\s+$(?u)",
              "regex": true
            }
          ]
        },
        {
          "type": "STRIP_NORMALIZER"
        }
      ]
    },
    "textPostprocessor": {
      "type": "MULTI_NORMALIZER",
      "children": [
        {
          "type": "TEXT_NORMALIZER"
        },
        {
          "type": "TEXT_REGULARIZER",
          "replacements": [
            {
              "old": "\\s+(?u)",
              "new": " ",
              "regex": true
            },
            {
              "old": "\\n(?u)",
              "regex": true
            },
            {
              "old": "^\\s+(?u)",
              "regex": true
            },
            {
              "old": "\\s+$(?u)",
              "regex": true
            }
          ]
        },
        {
          "type": "STRIP_NORMALIZER"
        }
      ]
    },
    "codec": {
      "charset": [
        "",
        " ",
        "&",
        "'",
        "(",
        ")",
        "*",
        ",",
        "-",
        ".",
        "0",
        "1",
        "2",
        "3",
        "4",
        "5",
        "6",
        "7",
        "8",
        "9",
        ":",
        ";",
        "?",
        "A",
        "B",
        "C",
        "D",
        "E",
        "F",
        "G",
        "H",
        "I",
        "J",
        "K",
        "L",
        "M",
        "N",
        "O",
        "P",
        "Q",
        "R",
        "S",
        "T",
        "U",
        "V",
        "X",
        "Y",
        "Z",
        "a",
        "b",
        "c",
        "d",
        "e",
        "f",
        "g",
        "h",
        "i",
        "j",
        "k",
        "l",
        "m",
        "n",
        "o",
        "p",
        "q",
        "r",
        "s",
        "t",
        "u",
        "v",
        "x",
        "y",
        "z",
        "\u00e0",
        "\u00e1",
        "\u00e2",
        "\u00e8",
        "\u00e9",
        "\u00ea",
        "\u00eb",
        "\u00ee",
        "\u00f2",
        "\u00f4",
        "\u00f9",
        "\u00fb",
        "\u0153",
        "\u0394",
        "!",
        "#",
        "=",
        "W",
        "^",
        "w",
        "{",
        "}",
        "\u00a7",
        "\u00b0",
        "\u00c7",
        "\u00c8",
        "\u00c9",
        "\u00ca",
        "\u00cf",
        "\u00e7",
        "\u00ef",
        "\u00fc",
        "\u0152",
        "\u039b",
        "\u03a0",
        "\u201c",
        "\u201e",
        "\u2020"
      ]
    }
  },
  "processes": 56,
  "maxIters": 1000000,
  "skipInvalidGt": true,
  "display": 100.0,
  "statsSize": 100,
  "batchSize": 5,
  "checkpointFrequency": -1.0,
  "outputDir": "/scratch/zpd/tmp/train_tmp/bin/fold_4",
  "iter": 89329,
  "lossStats": [
    0.013133184984326363,
    0.5987220406532288,
    0.02666212059557438,
    0.045734476298093796,
    0.007571626454591751,
    0.30766767263412476,
    4.131976127624512,
    0.20322850346565247,
    0.011508086696267128,
    13.010747909545898,
    0.06576156616210938,
    0.11609623581171036,
    0.11180642992258072,
    0.5629419088363647,
    0.006610077805817127,
    11.4707612991333,
    0.06971047818660736,
    0.015478618443012238,
    0.15060649812221527,
    1.809671401977539,
    0.06954804807901382,
    0.0104635925963521,
    1.9165546894073486,
    0.28535109758377075,
    0.10848428308963776,
    0.024019140750169754,
    3.8458118438720703,
    0.011783304624259472,
    0.04339578375220299,
    0.005108470097184181,
    0.01801137998700142,
    0.02229011245071888,
    0.11595501750707626,
    0.0025873405393213034,
    0.003768575144931674,
    0.18822257220745087,
    0.20747201144695282,
    0.0728997141122818,
    0.00784420408308506,
    2.3736977577209473,
    0.048123184591531754,
    3.265976667404175,
    0.017499176785349846,
    3.9404945373535156,
    0.006929734256118536,
    0.07862196862697601,
    7.6124982833862305,
    1.457271695137024,
    0.9135652780532837,
    0.13163216412067413,
    4.879403591156006,
    0.008978080004453659,
    0.8333626985549927,
    0.31673091650009155,
    0.027274027466773987,
    0.46000441908836365,
    2.3149895668029785,
    0.026000406593084335,
    0.018024854362010956,
    0.02596847340464592,
    0.023660454899072647,
    0.10475436598062515,
    0.35317081212997437,
    0.15876728296279907,
    0.017899923026561737,
    0.08102000504732132,
    0.04180186614394188,
    0.04582102224230766,
    0.05405799672007561,
    0.005468526855111122,
    0.007487982511520386,
    0.281227171421051,
    0.02101120539009571,
    7.362074851989746,
    0.07522387057542801,
    3.9141182899475098,
    0.3092072606086731,
    0.15371550619602203,
    0.0367375910282135,
    3.617182493209839,
    0.6720605492591858,
    0.23656567931175232,
    0.3340529203414917,
    0.11243655532598495,
    0.014406690374016762,
    0.02914319932460785,
    0.009118931367993355,
    0.003173923585563898,
    0.010421832092106342,
    0.16541042923927307,
    0.006348288152366877,
    0.01934080198407173,
    0.3983859121799469,
    0.618969738483429,
    0.017129767686128616,
    3.131711721420288,
    0.05328584462404251,
    0.7215323448181152,
    0.04468455910682678,
    0.04547039419412613
  ],
  "lerStats": [
    0.0,
    0.0055555556900799274,
    0.0,
    0.0,
    0.0,
    0.004999999888241291,
    0.11428572237491608,
    0.0058823530562222,
    0.0,
    0.06909091025590897,
    0.0,
    0.0,
    0.0,
    0.0054054055362939835,
    0.0,
    0.07000000029802322,
    0.0,
    0.0,
    0.0,
    0.010526316240429878,
    0.0,
    0.0,
    0.010526316240429878,
    0.004545454867184162,
    0.0,
    0.0,
    0.017378048971295357,
    0.0,
    0.0,
    0.0,
    0.0,
    0.0,
    0.0,
    0.0,
    0.0,
    0.0,
    0.0054054055362939835,
    0.0,
    0.0,
    0.01547619141638279,
    0.0,
    0.09059233963489532,
    0.0,
    0.15512821078300476,
    0.0,
    0.0,
    0.060465116053819656,
    0.005263158120214939,
    0.0057142856530845165,
    0.0,
    0.111111119389534,
    0.0,
    0.009302325546741486,
    0.0,
    0.0,
    0.0,
    0.08571428805589676,
    0.0,
    0.0,
    0.0,
    0.0,
    0.0,
    0.0058823530562222,
    0.0,
    0.0,
    0.0,
    0.0,
    0.0,
    0.0,
    0.0,
    0.0,
    0.009999999776482582,
    0.0,
    0.13333334028720856,
    0.0,
    0.1428571492433548,
    0.0,
    0.004545454867184162,
    0.0,
    0.15000000596046448,
    0.004761904943734407,
    0.0,
    0.006060606334358454,
    0.0,
    0.0,
    0.0,
    0.0,
    0.0,
    0.0,
    0.0,
    0.0,
    0.0,
    0.003921568859368563,
    0.023444976657629013,
    0.0,
    0.027272727340459824,
    0.0,
    0.004545454867184162,
    0.0,
    0.0
  ],
  "dtStats": [
    0.045806169509887695,
    0.046747684478759766,
    0.041986942291259766,
    0.0389866828918457,
    0.043561697006225586,
    0.03704237937927246,
    0.04449129104614258,
    0.04612278938293457,
    0.03827929496765137,
    0.049793243408203125,
    0.04027819633483887,
    0.04448246955871582,
    0.04241442680358887,
    0.04051804542541504,
    0.04190707206726074,
    0.04302167892456055,
    0.04485130310058594,
    0.03971362113952637,
    0.04091596603393555,
    0.04376816749572754,
    0.04352617263793945,
    0.03974103927612305,
    0.04066038131713867,
    0.04396963119506836,
    0.038817405700683594,
    0.04575014114379883,
    0.04462838172912598,
    0.04762101173400879,
    0.03777766227722168,
    0.043868064880371094,
    0.040975093841552734,
    0.04689621925354004,
    0.045619964599609375,
    0.04007697105407715,
    0.04309248924255371,
    0.05108141899108887,
    0.04707646369934082,
    0.04479646682739258,
    0.0456387996673584,
    0.041961669921875,
    0.04911994934082031,
    0.038719892501831055,
    0.04619097709655762,
    0.03941178321838379,
    0.0433807373046875,
    0.048981428146362305,
    0.04180622100830078,
    0.047072649002075195,
    0.044968605041503906,
    0.03924298286437988,
    0.04200601577758789,
    0.03751015663146973,
    0.0406033992767334,
    0.042435407638549805,
    0.044028282165527344,
    0.0446627140045166,
    0.04609179496765137,
    0.037796974182128906,
    0.042639732360839844,
    0.04194521903991699,
    0.04638385772705078,
    0.041492462158203125,
    0.042609214782714844,
    0.03439450263977051,
    0.03863835334777832,
    0.042316436767578125,
    0.0461277961730957,
    0.047479867935180664,
    0.043175697326660156,
    0.04498291015625,
    0.04446291923522949,
    0.040552616119384766,
    0.047353267669677734,
    0.04239964485168457,
    0.04144859313964844,
    0.04742169380187988,
    0.04732871055603027,
    0.0439302921295166,
    0.039203643798828125,
    0.040222883224487305,
    0.04212784767150879,
    0.0422365665435791,
    0.04520988464355469,
    0.046962738037109375,
    0.0428617000579834,
    0.04680681228637695,
    0.044194698333740234,
    0.046735286712646484,
    0.03268313407897949,
    0.04131150245666504,
    0.0460817813873291,
    0.05105137825012207,
    0.049657344818115234,
    0.043081045150756836,
    0.05300140380859375,
    0.04230856895446777,
    0.045165300369262695,
    0.04201555252075195,
    0.040598392486572266,
    0.03989434242248535
  ],
  "totalTime": 5368.52197265625,
  "earlyStoppingFrequency": -1.0,
  "earlyStoppingNbest": 5,
  "earlyStoppingBestModelPrefix": "4",
  "earlyStoppingBestAccuracy": 0.9900192618370056,
  "earlyStoppingBestCurNbest": 1,
  "earlyStoppingBestAtIter": 89330,
  "earlyStoppingBestModelOutputDir": "/scratch/zpd/tmp/models/bin",
  "outputModelPrefix": "model_",
  "dataAugRetrainOnOriginal": true,
  "version": 1
}