{
  "model": {
    "network": {
      "layers": [
        {
          "filters": 40,
          "kernelSize": {
            "x": 3,
            "y": 3
          },
          "stride": {
            "x": 1,
            "y": 1
          }
        },
        {
          "type": "MAX_POOLING",
          "kernelSize": {
            "x": 2,
            "y": 2
          },
          "stride": {
            "x": 2,
            "y": 2
          }
        },
        {
          "filters": 60,
          "kernelSize": {
            "x": 3,
            "y": 3
          },
          "stride": {
            "x": 1,
            "y": 1
          }
        },
        {
          "type": "MAX_POOLING",
          "kernelSize": {
            "x": 2,
            "y": 2
          },
          "stride": {
            "x": 2,
            "y": 2
          }
        },
        {
          "type": "LSTM",
          "hiddenNodes": 200
        }
      ],
      "solver": "ADAM_SOLVER",
      "dropout": 0.5,
      "features": 48,
      "classes": 178,
      "backend": {
        "cudnn": true,
        "randomSeed": 4
      },
      "ctcMergeRepeated": true,
      "learningRate": 0.0010000000474974513
    },
    "lineHeight": 48,
    "dataPreprocessor": {
      "lineHeight": 48,
      "pad": 16
    },
    "textPreprocessor": {
      "type": "MULTI_NORMALIZER",
      "children": [
        {
          "type": "TEXT_NORMALIZER"
        },
        {
          "type": "TEXT_REGULARIZER",
          "replacements": [
            {
              "old": "\u00b5",
              "new": "\u03bc"
            },
            {
              "old": "\u2013\u2014\u2014",
              "new": "-"
            },
            {
              "old": "\u2013\u2014",
              "new": "-"
            },
            {
              "old": "\ue644",
              "new": "\u00f6"
            },
            {
              "old": "o\u0364",
              "new": "\u00f6"
            },
            {
              "old": "\ue42c",
              "new": "\u00e4"
            },
            {
              "old": "a\u0364",
              "new": "\u00e4"
            },
            {
              "old": "\ue72b",
              "new": "\u00fc"
            },
            {
              "old": "u\u0364",
              "new": "\u00fc"
            },
            {
              "old": "\"",
              "new": "''"
            },
            {
              "old": "`",
              "new": "'"
            },
            {
              "old": "\u201c",
              "new": "''"
            },
            {
              "old": "\u201d",
              "new": "''"
            },
            {
              "old": "\u00b4",
              "new": "'"
            },
            {
              "old": "\u2018",
              "new": "'"
            },
            {
              "old": "\u2019",
              "new": "'"
            },
            {
              "old": "\u201c",
              "new": "''"
            },
            {
              "old": "\u201d",
              "new": "''"
            },
            {
              "old": "\u201c",
              "new": "''"
            },
            {
              "old": "\u201e",
              "new": ",,"
            },
            {
              "old": "\u2026",
              "new": "..."
            },
            {
              "old": "\u2032",
              "new": "'"
            },
            {
              "old": "\u2033",
              "new": "''"
            },
            {
              "old": "\u2034",
              "new": "'''"
            },
            {
              "old": "\u3003",
              "new": "''"
            },
            {
              "old": "''",
              "new": "\""
            },
            {
              "old": "\\s+(?u)",
              "new": " ",
              "regex": true
            },
            {
              "old": "\\n(?u)",
              "regex": true
            },
            {
              "old": "^\\s+(?u)",
              "regex": true
            },
            {
              "old": "\\s+$(?u)",
              "regex": true
            }
          ]
        },
        {
          "type": "STRIP_NORMALIZER"
        }
      ]
    },
    "textPostprocessor": {
      "type": "MULTI_NORMALIZER",
      "children": [
        {
          "type": "TEXT_NORMALIZER"
        },
        {
          "type": "TEXT_REGULARIZER",
          "replacements": [
            {
              "old": "\u00b5",
              "new": "\u03bc"
            },
            {
              "old": "\u2013\u2014\u2014",
              "new": "-"
            },
            {
              "old": "\u2013\u2014",
              "new": "-"
            },
            {
              "old": "\ue644",
              "new": "\u00f6"
            },
            {
              "old": "o\u0364",
              "new": "\u00f6"
            },
            {
              "old": "\ue42c",
              "new": "\u00e4"
            },
            {
              "old": "a\u0364",
              "new": "\u00e4"
            },
            {
              "old": "\ue72b",
              "new": "\u00fc"
            },
            {
              "old": "u\u0364",
              "new": "\u00fc"
            },
            {
              "old": "\"",
              "new": "''"
            },
            {
              "old": "`",
              "new": "'"
            },
            {
              "old": "\u201c",
              "new": "''"
            },
            {
              "old": "\u201d",
              "new": "''"
            },
            {
              "old": "\u00b4",
              "new": "'"
            },
            {
              "old": "\u2018",
              "new": "'"
            },
            {
              "old": "\u2019",
              "new": "'"
            },
            {
              "old": "\u201c",
              "new": "''"
            },
            {
              "old": "\u201d",
              "new": "''"
            },
            {
              "old": "\u201c",
              "new": "''"
            },
            {
              "old": "\u201e",
              "new": ",,"
            },
            {
              "old": "\u2026",
              "new": "..."
            },
            {
              "old": "\u2032",
              "new": "'"
            },
            {
              "old": "\u2033",
              "new": "''"
            },
            {
              "old": "\u2034",
              "new": "'''"
            },
            {
              "old": "\u3003",
              "new": "''"
            },
            {
              "old": "''",
              "new": "\""
            },
            {
              "old": "\\s+(?u)",
              "new": " ",
              "regex": true
            },
            {
              "old": "\\n(?u)",
              "regex": true
            },
            {
              "old": "^\\s+(?u)",
              "regex": true
            },
            {
              "old": "\\s+$(?u)",
              "regex": true
            }
          ]
        },
        {
          "type": "STRIP_NORMALIZER"
        }
      ]
    },
    "codec": {
      "charset": [
        "",
        " ",
        "&",
        "'",
        "(",
        ")",
        "*",
        ",",
        "-",
        ".",
        "/",
        "0",
        "1",
        "2",
        "3",
        "4",
        "5",
        "6",
        "7",
        "8",
        "9",
        ":",
        ";",
        "?",
        "A",
        "B",
        "C",
        "D",
        "E",
        "F",
        "G",
        "H",
        "I",
        "J",
        "K",
        "L",
        "M",
        "N",
        "O",
        "P",
        "Q",
        "R",
        "S",
        "T",
        "U",
        "V",
        "X",
        "Y",
        "Z",
        "[",
        "]",
        "a",
        "b",
        "c",
        "d",
        "e",
        "f",
        "g",
        "h",
        "i",
        "j",
        "k",
        "l",
        "m",
        "n",
        "o",
        "p",
        "q",
        "r",
        "s",
        "t",
        "u",
        "v",
        "x",
        "y",
        "z",
        "\u00b6",
        "\u00b7",
        "\u00c0",
        "\u00c6",
        "\u00d2",
        "\u00d3",
        "\u00df",
        "\u00e0",
        "\u00e1",
        "\u00e2",
        "\u00e3",
        "\u00e4",
        "\u00e6",
        "\u00e8",
        "\u00e9",
        "\u00ea",
        "\u00eb",
        "\u00ec",
        "\u00ed",
        "\u00ee",
        "\u00f1",
        "\u00f2",
        "\u00f3",
        "\u00f4",
        "\u00f5",
        "\u00f9",
        "\u00fa",
        "\u00fb",
        "\u0111",
        "\u0119",
        "\u0129",
        "\u0142",
        "\u0153",
        "\u0169",
        "\u017f",
        "\u0292",
        "\u0301",
        "\u0303",
        "\u0391",
        "\u0394",
        "\u03a6",
        "\u03ac",
        "\u03ad",
        "\u03ae",
        "\u03af",
        "\u03b1",
        "\u03b2",
        "\u03b3",
        "\u03b4",
        "\u03b5",
        "\u03b6",
        "\u03b7",
        "\u03b8",
        "\u03b9",
        "\u03ba",
        "\u03bb",
        "\u03bc",
        "\u03bd",
        "\u03be",
        "\u03bf",
        "\u03c0",
        "\u03c1",
        "\u03c2",
        "\u03c3",
        "\u03c4",
        "\u03c5",
        "\u03c6",
        "\u03c7",
        "\u03c8",
        "\u03c9",
        "\u03cb",
        "\u03cc",
        "\u03cd",
        "\u03ce",
        "\u03d6",
        "\u03df",
        "\u1d10",
        "\u1dd1",
        "\u1dd3",
        "\u1de3",
        "\u1e9c",
        "\u1ebd",
        "\u1f00",
        "\u1f10",
        "\u1f41",
        "\u1f74",
        "\u1f78",
        "\u1fe6",
        "\u204a",
        "\u2132",
        "\u2183",
        "\u2184",
        "\u2e17",
        "\ua751",
        "\ua753",
        "\ua757",
        "\ua758",
        "\ua759",
        "\ua75b",
        "\ua75d",
        "\ua770",
        "\ua776"
      ]
    }
  },
  "processes": 32,
  "maxIters": 1000000,
  "skipInvalidGt": true,
  "display": 100,
  "statsSize": 100,
  "batchSize": 5,
  "checkpointFrequency": 50000,
  "outputDir": "/home/ls6/reul/temp/mixed_antiqua_old/fold_4",
  "iter": 99999,
  "lossStats": [
    0.9026734232902527,
    0.09489703178405762,
    0.8997498750686646,
    0.1764996200799942,
    0.01959497295320034,
    0.24943247437477112,
    0.8242155313491821,
    0.04227562993764877,
    0.018498362973332405,
    0.05111159756779671,
    0.17792493104934692,
    0.08941943943500519,
    0.007282627280801535,
    1.0420396327972412,
    0.005395418964326382,
    0.053772591054439545,
    1.3545219898223877,
    0.5620390176773071,
    0.1299939602613449,
    0.2234841287136078,
    0.1568102240562439,
    0.2709418833255768,
    0.5798129439353943,
    0.08758576959371567,
    0.11495848000049591,
    0.012058212421834469,
    0.09039400517940521,
    0.169663667678833,
    0.1513734608888626,
    0.24162621796131134,
    0.7672455906867981,
    0.03518890589475632,
    1.7314494848251343,
    0.03569399565458298,
    0.004843445494771004,
    0.37229490280151367,
    0.006881043314933777,
    0.06652164459228516,
    0.666875422000885,
    0.1025959700345993,
    0.03749992698431015,
    0.2724582850933075,
    0.8088038563728333,
    0.514224648475647,
    0.3582705855369568,
    0.0020631374791264534,
    0.005324759520590305,
    0.053667087107896805,
    0.03911183029413223,
    0.04325433820486069,
    0.033294275403022766,
    1.0084940195083618,
    0.9338961839675903,
    0.01629466563463211,
    0.24278493225574493,
    0.2270309180021286,
    0.40313664078712463,
    0.09679342806339264,
    0.659358024597168,
    0.02489941008388996,
    0.026050686836242676,
    0.5058130025863647,
    1.6992676258087158,
    0.04107706621289253,
    0.10865940153598785,
    0.02917526662349701,
    0.4585813581943512,
    0.04939017444849014,
    0.3132566213607788,
    0.006197528913617134,
    0.01930363103747368,
    0.1652209311723709,
    0.08000679314136505,
    0.037035148590803146,
    0.9563454389572144,
    0.11647830158472061,
    1.657065987586975,
    0.1451244056224823,
    0.048458270728588104,
    0.002907421672716737,
    0.15568247437477112,
    0.02520197629928589,
    0.013832606375217438,
    0.46722230315208435,
    1.181110143661499,
    0.0029893224127590656,
    0.09294994175434113,
    0.073014996945858,
    1.7193233966827393,
    0.023973867297172546,
    0.04007164388895035,
    0.6449311375617981,
    0.7491326928138733,
    0.18869861960411072,
    0.09071367233991623,
    0.01946422830224037,
    0.024753117933869362,
    0.03757597133517265,
    0.04055671766400337,
    0.866213321685791
  ],
  "lerStats": [
    0.0031746034510433674,
    0.0,
    0.002247191034257412,
    0.002816901309415698,
    0.0,
    0.0058823530562222,
    0.004347826354205608,
    0.0,
    0.0,
    0.0,
    0.003508772002533078,
    0.0,
    0.0,
    0.010762007907032967,
    0.0,
    0.0,
    0.0051282052882015705,
    0.0058823530562222,
    0.0,
    0.006896551698446274,
    0.0,
    0.004444444552063942,
    0.01666666753590107,
    0.0,
    0.0,
    0.0,
    0.0,
    0.0,
    0.0,
    0.0,
    0.019999999552965164,
    0.0,
    0.008301405236124992,
    0.0,
    0.0,
    0.005063291173428297,
    0.0,
    0.0,
    0.0031250000465661287,
    0.0,
    0.0,
    0.0,
    0.004444444552063942,
    0.004081632476300001,
    0.01818181946873665,
    0.0,
    0.0,
    0.0,
    0.0,
    0.0,
    0.0,
    0.007843137718737125,
    0.011282356455922127,
    0.0,
    0.0,
    0.0,
    0.007999999448657036,
    0.0,
    0.003030303167179227,
    0.0,
    0.0,
    0.004651162773370743,
    0.0023809524718672037,
    0.0,
    0.0,
    0.0,
    0.019999999552965164,
    0.0,
    0.0027027027681469917,
    0.0,
    0.0,
    0.0,
    0.0,
    0.0,
    0.0023255813866853714,
    0.0,
    0.0065488568507134914,
    0.0,
    0.0,
    0.0,
    0.004166666883975267,
    0.0,
    0.0,
    0.015384616330265999,
    0.012329931370913982,
    0.0,
    0.0,
    0.0,
    0.004878048785030842,
    0.0,
    0.0,
    0.00620192289352417,
    0.004651162773370743,
    0.0,
    0.0,
    0.0,
    0.0,
    0.0,
    0.0,
    0.0036363634280860424
  ],
  "dtStats": [
    0.04673290252685547,
    0.05231165885925293,
    0.04705381393432617,
    0.04666876792907715,
    0.04998493194580078,
    0.04091691970825195,
    0.04557442665100098,
    0.03522205352783203,
    0.03852725028991699,
    0.05217766761779785,
    0.040595293045043945,
    0.038945913314819336,
    0.04765820503234863,
    0.032279253005981445,
    0.023085355758666992,
    0.04381990432739258,
    0.03624081611633301,
    0.03766441345214844,
    0.04467201232910156,
    0.04809403419494629,
    0.04781389236450195,
    0.03804755210876465,
    0.04068946838378906,
    0.04282259941101074,
    0.04176783561706543,
    0.042958736419677734,
    0.03145742416381836,
    0.03942418098449707,
    0.045777082443237305,
    0.045996665954589844,
    0.029886960983276367,
    0.04361152648925781,
    0.05043768882751465,
    0.04228067398071289,
    0.037758588790893555,
    0.05144643783569336,
    0.02416372299194336,
    0.02477741241455078,
    0.03491520881652832,
    0.03556060791015625,
    0.0420832633972168,
    0.04680800437927246,
    0.043146610260009766,
    0.029399394989013672,
    0.03937053680419922,
    0.0393519401550293,
    0.043671607971191406,
    0.0429685115814209,
    0.04907059669494629,
    0.04226326942443848,
    0.0369572639465332,
    0.027462482452392578,
    0.03197073936462402,
    0.03429698944091797,
    0.0375363826751709,
    0.03710603713989258,
    0.048239946365356445,
    0.04880023002624512,
    0.03741860389709473,
    0.05037951469421387,
    0.0328831672668457,
    0.05321502685546875,
    0.04945516586303711,
    0.04407835006713867,
    0.04918360710144043,
    0.04266476631164551,
    0.02089691162109375,
    0.04232025146484375,
    0.04520916938781738,
    0.04654717445373535,
    0.02186298370361328,
    0.038840532302856445,
    0.04541373252868652,
    0.03262782096862793,
    0.049762725830078125,
    0.04013490676879883,
    0.04038834571838379,
    0.0453944206237793,
    0.03496098518371582,
    0.03409314155578613,
    0.04684877395629883,
    0.04420876502990723,
    0.035156965255737305,
    0.03600144386291504,
    0.05126500129699707,
    0.04365229606628418,
    0.036687374114990234,
    0.04749274253845215,
    0.03951382637023926,
    0.035752058029174805,
    0.0325169563293457,
    0.040750980377197266,
    0.04710268974304199,
    0.035421133041381836,
    0.052847862243652344,
    0.025905132293701172,
    0.04947066307067871,
    0.052088260650634766,
    0.030158281326293945,
    0.04140114784240723
  ],
  "totalTime": 5097.93017578125,
  "earlyStoppingFrequency": 50000,
  "earlyStoppingNbest": 10,
  "earlyStoppingBestModelPrefix": "4",
  "earlyStoppingBestAccuracy": 0.990829348564148,
  "earlyStoppingBestCurNbest": 1,
  "earlyStoppingBestAtIter": 100000,
  "earlyStoppingBestModelOutputDir": "/scratch/Datensets_Bildverarbeitung/OCR/GT4HistOCR/mixed_antiqua_old//models/",
  "outputModelPrefix": "model_"
}